torchort/__init__.py
torchort-0.0.8.dev20210317.dist-info/LICENSE
torchort-0.0.8.dev20210317.dist-info/METADATA
torchort-0.0.8.dev20210317.dist-info/WHEEL
torchort-0.0.8.dev20210317.dist-info/top_level.txt
torchort-0.0.8.dev20210317.dist-info/RECORD
