Metadata-Version: 2.1
Name: torchort
Version: 0.0.8.dev20210317
Summary: training Pytorch models with onnxruntime
Home-page: https://github.com/pytorch/ort
Author: torchort contributors
License: UNKNOWN
Project-URL: Bug Tracker, https://github.com/pytorch/ort/issues
Platform: UNKNOWN
Classifier: Programming Language :: Python :: 3
Classifier: License :: OSI Approved :: MIT License
Classifier: Operating System :: OS Independent
Requires-Python: >=3.6
